autowork/__init__.py
autowork/autowork.py
autowork/autowork_AssistantAgent.py
autowork/autowork_CodeExecutorAgent.py
autowork/autowork_ModelClient.py
autowork/autowork_Termination.py
autowork/autowork_UserProxyAgent.py
autowork-0.4.1.2.dist-info/LICENSE
autowork-0.4.1.2.dist-info/METADATA
autowork-0.4.1.2.dist-info/WHEEL
autowork-0.4.1.2.dist-info/entry_points.txt
autowork-0.4.1.2.dist-info/top_level.txt
autowork-0.4.1.2.dist-info/RECORD
