Metadata-Version: 2.2
Name: autowork
Version: 0.4.1.2
Summary: autowork to automatically process the task (write code and execute it) based on LLM.
Home-page: https://github.com/yingjiewei/autowork
Author: Yingjie Wei
Author-email: yingjie.wei@qq.com
Classifier: Programming Language :: Python :: 3
Classifier: License :: OSI Approved :: MIT License
Classifier: Operating System :: OS Independent
Requires-Python: >=3.8
License-File: LICENSE
Dynamic: author
Dynamic: author-email
Dynamic: classifier
Dynamic: description
Dynamic: description-content-type
Dynamic: home-page
Dynamic: requires-python
Dynamic: summary
